examples/__init__.py
examples/example_usage.py
selenium_ui_test_tool/__init__.py
selenium_ui_test_tool/assert_text_present/__init__.py
selenium_ui_test_tool/assert_text_present/assert_text_present.py
selenium_ui_test_tool/base_test/__init__.py
selenium_ui_test_tool/base_test/base_test.py
selenium_ui_test_tool/click_element/__init__.py
selenium_ui_test_tool/click_element/click_element.py
selenium_ui_test_tool/click_on/__init__.py
selenium_ui_test_tool/click_on/click_on.py
selenium_ui_test_tool/config_actions/__init__.py
selenium_ui_test_tool/config_actions/config_actions.py
selenium_ui_test_tool/driver_builder/__init__.py
selenium_ui_test_tool/driver_builder/driver_builder.py
selenium_ui_test_tool/fill_input/__init__.py
selenium_ui_test_tool/fill_input/fill_input.py
selenium_ui_test_tool/fill_login_form/__init__.py
selenium_ui_test_tool/fill_login_form/fill_login_form.py
selenium_ui_test_tool/fill_login_form_with_confirm_password/__init__.py
selenium_ui_test_tool/fill_login_form_with_confirm_password/fill_login_form_with_confirm_password.py
selenium_ui_test_tool/get_env_var/__init__.py
selenium_ui_test_tool/get_env_var/get_env_var.py
selenium_ui_test_tool/get_url/__init__.py
selenium_ui_test_tool/get_url/get_url.py
selenium_ui_test_tool/upload_file/__init__.py
selenium_ui_test_tool/upload_file/upload_file.py
selenium_ui_test_tool/wait_element/__init__.py
selenium_ui_test_tool/wait_element/wait_elements.py
selenium_ui_test_tool-2.1.2.dist-info/licenses/LICENSE
selenium_ui_test_tool-2.1.2.dist-info/METADATA
selenium_ui_test_tool-2.1.2.dist-info/WHEEL
selenium_ui_test_tool-2.1.2.dist-info/top_level.txt
selenium_ui_test_tool-2.1.2.dist-info/RECORD
