Metadata-Version: 2.4
Name: selenium-ui-test-tool
Version: 2.1.2
Summary: Python library that simplifies Selenium WebDriver UI test automation
Home-page: https://kingcrud12.github.io/selenium_ui_test_tool/
Author: Yann Dipita
Author-email: Yann Dipita <dipitay@gmail.com>
License: MIT
Keywords: selenium,testing,ui,automation,webdriver
Classifier: Development Status :: 4 - Beta
Classifier: Intended Audience :: Developers
Classifier: License :: OSI Approved :: MIT License
Classifier: Programming Language :: Python :: 3
Classifier: Programming Language :: Python :: 3.8
Classifier: Programming Language :: Python :: 3.9
Classifier: Programming Language :: Python :: 3.10
Classifier: Programming Language :: Python :: 3.11
Classifier: Topic :: Software Development :: Testing
Requires-Python: >=3.8
License-File: LICENSE
Requires-Dist: selenium>=4.15.0
Requires-Dist: python-dotenv>=1.0.0
Requires-Dist: webdriver-manager>=4.0.1
Provides-Extra: dev
Requires-Dist: pytest>=7.0.0; extra == "dev"
Requires-Dist: black>=23.0.0; extra == "dev"
Requires-Dist: flake8>=6.0.0; extra == "dev"
Dynamic: author
Dynamic: home-page
Dynamic: license-file
Dynamic: requires-python
